mangroves/__init__.py
mangroves/mangrove.py
mangroves-1.0.1.dist-info/LICENSE
mangroves-1.0.1.dist-info/METADATA
mangroves-1.0.1.dist-info/WHEEL
mangroves-1.0.1.dist-info/top_level.txt
mangroves-1.0.1.dist-info/RECORD
